{"name":"build-javascript","namedChunkGroups":{"app":{"name":"app","assets":[{"name":"webpack-runtime-b5c4252e3081e9705ae7.js","size":3523},{"name":"framework-e4f0647456b685c25190.js","size":140717},{"name":"app-8e47e0f0fee6336e5762.js","size":62056}],"filteredAssets":0,"assetsSize":206296,"filteredAuxiliaryAssets":3,"auxiliaryAssetsSize":595615},"component---src-pages-404-js":{"name":"component---src-pages-404-js","assets":[{"name":"component---src-pages-404-js-a247705ad3b6b7912ad6.js","size":756}],"filteredAssets":0,"assetsSize":756,"filteredAuxiliaryAssets":1,"auxiliaryAssetsSize":1735},"component---src-pages-index-js":{"name":"component---src-pages-index-js","assets":[{"name":"component---src-pages-index-js-acf6631ac36e0c1b5fa5.js","size":3805}],"filteredAssets":0,"assetsSize":3805,"filteredAuxiliaryAssets":1,"auxiliaryAssetsSize":7340}},"assetsByChunkName":{"app":["webpack-runtime-b5c4252e3081e9705ae7.js","framework-e4f0647456b685c25190.js","app-8e47e0f0fee6336e5762.js"],"component---src-pages-404-js":["component---src-pages-404-js-a247705ad3b6b7912ad6.js"],"component---src-pages-index-js":["component---src-pages-index-js-acf6631ac36e0c1b5fa5.js"]},"childAssetsByChunkName":{}}